agilentaspparser/__init__.py
agilentaspparser/agilent.py
agilentaspparser-0.0.4.dist-info/LICENSE
agilentaspparser-0.0.4.dist-info/METADATA
agilentaspparser-0.0.4.dist-info/WHEEL
agilentaspparser-0.0.4.dist-info/top_level.txt
agilentaspparser-0.0.4.dist-info/RECORD
