Metadata-Version: 2.1
Name: agilentaspparser
Version: 0.0.4
Summary: Parser for Agilent IR .asp files
Home-page: https://github.com/egonik-unlp/agilent_ir
Author: Eduardo Gonik
Author-email: gonik@quimica.unlp.edu.ar
License: UNKNOWN
Platform: UNKNOWN
Classifier: Programming Language :: Python :: 3
Classifier: License :: OSI Approved :: MIT License
Classifier: Operating System :: OS Independent
Requires-Python: >=3.6
